tests/__init__.py
tests/conftest.py
tests/test_push_pull.py
vlmsw/__init__.py
vlmsw/common.py
vlmsw/exceptions.py
vlmsw/pull.py
vlmsw/push.py
vlmsw/push_converted_weights.py
vlmsw/settings/__init__.py
vlmsw/settings/settings.py
tiktokmaxim_vlmsw-0.1.1.dist-info/METADATA
tiktokmaxim_vlmsw-0.1.1.dist-info/WHEEL
tiktokmaxim_vlmsw-0.1.1.dist-info/top_level.txt
tiktokmaxim_vlmsw-0.1.1.dist-info/RECORD
