Metadata-Version: 2.1
Name: tiktokmaxim_vlmsw
Version: 0.1.1
Summary: Краткое описание вашей библиотеки
Home-page: https://github.com/tktk-maxim/vlmsw
Author: Max
Author-email: masya3_03@mail.com
Classifier: Programming Language :: Python :: 3
Classifier: License :: OSI Approved :: MIT License
Classifier: Operating System :: OS Independent
Requires-Python: >=3.10
